datacube_wps/__init__.py
datacube_wps/impl.py
datacube_wps/startup_utils.py
datacube_wps/processes/__init__.py
datacube_wps/processes/fcdrill.py
datacube_wps/processes/mangrovedrill.py
datacube_wps/processes/witprocess.py
datacube_wps/processes/wofsdrill.py
tests/__init__.py
tests/conftest.py
tests/test_api.py
tests/test_request_parsing.py
tests/test_s3.py
tests/test_webapp.py
datacube_wps-0.4.11.dist-info/LICENSE
datacube_wps-0.4.11.dist-info/METADATA
datacube_wps-0.4.11.dist-info/WHEEL
datacube_wps-0.4.11.dist-info/top_level.txt
datacube_wps-0.4.11.dist-info/RECORD
