Metadata-Version: 2.1
Name: datacube-wps
Version: 0.4.11
Summary: datacube-wps is an implementation of the Web Processing Service standard from the Open Geospatial Consortium.
Home-page: http://www.ga.gov.au/dea
Author: Digital Earth Australia
Author-email: earth.observation@ga.gov.au
Maintainer: Digital Earth Australia
Maintainer-email: earth.observation@ga.gov.au
License: Apache License 2.0
Download-URL: https://github.com/opendatacube/datacube-wps
Keywords: ODC WPS OGC processing
Platform: all
Classifier: Development Status :: 4 - Beta
Classifier: Environment :: Web Environment
Classifier: Intended Audience :: Developers
Classifier: Intended Audience :: Science/Research
Classifier: License :: OSI Approved :: Apache Software License
Classifier: Operating System :: OS Independent
Classifier: Programming Language :: Python
Classifier: Topic :: Scientific/Engineering :: GIS
License-File: LICENSE
Requires-Dist: flask
Requires-Dist: gunicorn
Requires-Dist: datacube
Requires-Dist: altair
Requires-Dist: altair-saver
Requires-Dist: python-dateutil
Requires-Dist: sentry-sdk[flask]
Requires-Dist: blinker
Requires-Dist: prometheus-flask-exporter
Requires-Dist: pywps
Requires-Dist: pyarrow
